CHANGELOG
INSTALL
LICENSE.txt
MANIFEST.in
Makefile
README.md
VERSION
config.dist.py
configure.sh
pyproject.toml
pytest.ini
setup.cfg
setup.py
charm/__init__.py
charm/config.py
charm/adapters/__init__.py
charm/adapters/abenc_adapt_hybrid.py
charm/adapters/dabenc_adapt_hybrid.py
charm/adapters/ibenc_adapt_hybrid.py
charm/adapters/ibenc_adapt_identityhash.py
charm/adapters/kpabenc_adapt_hybrid.py
charm/adapters/pkenc_adapt_bchk05.py
charm/adapters/pkenc_adapt_chk04.py
charm/adapters/pkenc_adapt_hybrid.py
charm/adapters/pksig_adapt_naor01.py
charm/core/__init__.py
charm/core/benchmark/benchmark_util.c
charm/core/benchmark/benchmark_util.h
charm/core/benchmark/benchmarkmodule.c
charm/core/benchmark/benchmarkmodule.h
charm/core/crypto/__init__.py
charm/core/crypto/AES/AES.c
charm/core/crypto/DES/DES.c
charm/core/crypto/DES3/DES3.c
charm/core/crypto/cryptobase/XOR.c
charm/core/crypto/cryptobase/_counter.c
charm/core/crypto/cryptobase/_counter.h
charm/core/crypto/cryptobase/block_template.c
charm/core/crypto/cryptobase/block_template.h
charm/core/crypto/cryptobase/cryptobasemodule.c
charm/core/crypto/cryptobase/stream_template.c
charm/core/crypto/cryptobase/strxor.c
charm/core/crypto/cryptobase/libtom/tomcrypt.h
charm/core/crypto/cryptobase/libtom/tomcrypt_argchk.h
charm/core/crypto/cryptobase/libtom/tomcrypt_cfg.h
charm/core/crypto/cryptobase/libtom/tomcrypt_cipher.h
charm/core/crypto/cryptobase/libtom/tomcrypt_custom.h
charm/core/crypto/cryptobase/libtom/tomcrypt_des.c
charm/core/crypto/cryptobase/libtom/tomcrypt_hash.h
charm/core/crypto/cryptobase/libtom/tomcrypt_mac.h
charm/core/crypto/cryptobase/libtom/tomcrypt_macros.h
charm/core/crypto/cryptobase/libtom/tomcrypt_math.h
charm/core/crypto/cryptobase/libtom/tomcrypt_misc.h
charm/core/crypto/cryptobase/libtom/tomcrypt_pk.h
charm/core/crypto/cryptobase/libtom/tomcrypt_pkcs.h
charm/core/crypto/cryptobase/libtom/tomcrypt_prng.h
charm/core/engine/__init__.py
charm/core/engine/protocol.py
charm/core/engine/util.py
