Metadata-Version: 2.4
Name: charm-crypto-framework
Version: 0.60
Summary: Charm is a framework for rapid prototyping of cryptosystems
Home-page: https://charm-crypto.io/
Author: J. Ayo Akinyele
Author-email: "J. Ayo Akinyele" <jakinye3@jhu.edu>
Maintainer-email: "J. Ayo Akinyele" <jakinye3@jhu.edu>
License: LGPL-3.0-or-later
Project-URL: Homepage, https://charm-crypto.io/
Project-URL: Documentation, https://charm-crypto.io/documentation
Project-URL: Repository, https://github.com/JHUISI/charm
Project-URL: Issues, https://github.com/JHUISI/charm/issues
Project-URL: Changelog, https://github.com/JHUISI/charm/blob/master/CHANGELOG
Keywords: cryptography,pairing-based cryptography,attribute-based encryption,identity-based encryption,digital signatures,elliptic curves,bilinear pairings
Classifier: Development Status :: 4 - Beta
Classifier: Intended Audience :: Developers
Classifier: Intended Audience :: Science/Research
Classifier: License :: OSI Approved :: GNU Lesser General Public License v3 or later (LGPLv3+)
Classifier: Operating System :: MacOS :: MacOS X
Classifier: Operating System :: POSIX :: Linux
Classifier: Operating System :: Microsoft :: Windows
Classifier: Programming Language :: Python :: 3
Classifier: Programming Language :: Python :: 3.8
Classifier: Programming Language :: Python :: 3.9
Classifier: Programming Language :: Python :: 3.10
Classifier: Programming Language :: Python :: 3.11
Classifier: Programming Language :: Python :: 3.12
Classifier: Programming Language :: C
Classifier: Topic :: Security :: Cryptography
Classifier: Topic :: Software Development :: Libraries :: Python Modules
Requires-Python: >=3.8
License-File: LICENSE.txt
Requires-Dist: pyparsing<4.0,>=2.1.5
Provides-Extra: dev
Requires-Dist: pytest>=7.0; extra == "dev"
Requires-Dist: hypothesis>=6.0; extra == "dev"
Requires-Dist: build; extra == "dev"
Requires-Dist: twine; extra == "dev"
Provides-Extra: docs
Requires-Dist: sphinx>=4.0; extra == "docs"
Requires-Dist: sphinx-rtd-theme; extra == "docs"
Dynamic: author
Dynamic: home-page
Dynamic: license-file
Dynamic: requires-python
